foliant/preprocessors/customids.py
foliantcontrib.customids-1.0.8.dist-info/LICENSE
foliantcontrib.customids-1.0.8.dist-info/METADATA
foliantcontrib.customids-1.0.8.dist-info/WHEEL
foliantcontrib.customids-1.0.8.dist-info/top_level.txt
foliantcontrib.customids-1.0.8.dist-info/RECORD
