Metadata-Version: 2.1
Name: foliantcontrib.customids
Version: 1.0.8
Summary: Custom heading IDs for Foliant.
Home-page: https://github.com/foliant-docs/foliantcontrib.customids
Author: Sergey Kanunnikov
Author-email: sergey.kanunnikov@gmail.com
License: MIT
Platform: any
Classifier: Development Status :: 5 - Production/Stable
Classifier: Environment :: Console
Classifier: Intended Audience :: Developers
Classifier: License :: OSI Approved :: MIT License
Classifier: Operating System :: OS Independent
Classifier: Programming Language :: Python
Classifier: Topic :: Documentation
Classifier: Topic :: Utilities
License-File: LICENSE
Requires-Dist: foliant >=1.0.4
Requires-Dist: foliantcontrib.utils >=1.0.0
